{
    "themes": {
        "academy": {
          "daysOfBirth": {
            "1": "curioso(a)",
            "2": "exageradamente dedicado(a)",
            "3": "inteligente",
            "4": "perseverante",
            "5": "inovador(a)",
            "6": "com síndrome de impostor",
            "7": "criativo(a)",
            "8": "procrastinador",
            "9": "sociável",
            "10": "ambicioso(a)",
            "11": "corrupto(a)",
            "12": "visionário(a)",
            "13": "disciplinado(a)",
            "14": "que detestava trabalhar em equipe",
            "15": "responsável",
            "16": "que queria ser coach",
            "17": "inquisitivo(a)",
            "18": "competente",
            "19": "comprometido(a)",
            "20": "resiliente como PEDRA",
            "21": "que era um espião da Samsung",
            "22": "altruista",
            "23": "empático(a)",
            "24": "que odiava café",
            "25": "preguiçoso(a)",
            "26": "viciado em debugar",
            "27": "autodidata",
            "28": "articulado(a) como o demônio",
            "29": "brutalmente honesto(a)",
            "30": "com burnout",
            "31": "que sucumbiu à loucura"
          },
          "birthMonths": {
            "1": "embaixador(a)",
            "2": "pesquisador(a)",
            "3": "mentor(a)",
            "4": "cientista de dados",
            "5": "engenheiro(a) de software",
            "6": "designer",
            "7": "programador(a)",
            "8": "arquiteto(a)",
            "9": "IA",
            "10": "gerente",
            "11": "gamedev",
            "12": "QA"
          },
          "initialLetters": {
            "A": "Era uma vez um(a)",
            "B": "O segundo recomeço do(a)",
            "C": "As aventuras intrigantes do(a)",
            "D": "O mistério acadêmico do(a)",
            "E": "A jornada cansativa, porém digna do(a)",
            "F": "O enigma estudantil do(a)",
            "G": "O reencontro agradável de um(a)",
            "H": "A história desconhecida do(a)",
            "I": "Os segredos de um(a)",
            "J": "A lenda  estupenda do(a)",
            "K": "A magia encantadora do(a)",
            "L": "A redenção paciente do(a)",
            "M": "A promessa cativante do(a)",
            "N": "O renascimento criativo do(a)",
            "O": "A vingança debochada do(a)",
            "P": "A fuga do(a)",
            "Q": "A descoberta empolgada do(a)",
            "R": "Os sonhos eufóricos de um(a)",
            "S": "A conspiração fabulosa do(a)",
            "T": "A rebelião gloriosa do(a)",
            "U": "O destino majestoso do(a)",
            "V": "O caminho nostálgico do(a)",
            "W": "A trajetória perfeccionista do(a)",
            "X": "O despertar notável do(a)",
            "Y": "O progresso serelepe do(a)",
            "Z": "A luta sublime do(a)"
          }
        },
        "criminal": {
          "daysOfBirth": {
            "1": "medroso(a)",
            "2": "audacioso(a)",
            "3": "manipulador(a)",
            "4": "perigoso(a)",
            "5": "astuto(a)",
            "6": "implacável",
            "7": "mercenário(a)",
            "8": "arrependido(a)",
            "9": "traidor(a)",
            "10": "violento(a)",
            "11": "calculista(a)",
            "12": "sedutor(a)",
            "13": "obsessivo(a)",
            "14": "trapaceiro(a)",
            "15": "do Pix",
            "16": "corrupto(a)",
            "17": "sádico(a)",
            "18": "injusto(a)",
            "19": "chantagista",
            "20": "sem juízo",
            "21": "vigarista",
            "22": "desonesto(a)",
            "23": "implusivo(a)",
            "24": "duas-caras",
            "25": "pervertido(a)",
            "26": "cruel",
            "27": "insensível",
            "28": "mentiroso(a)",
            "29": "de corações",
            "30": "desalmado(a)",
            "31": "assassino(a)"
          },
          "birthMonths": {
            "1": "mafioso(a)",
            "2": "laranja",
            "3": "assaltante",
            "4": "detetive",
            "5": "traficante",
            "6": "juiz(a)",
            "7": "sequestrador(a)",
            "8": "sonegador(a)",
            "9": "contrabandista",
            "10": "perito(a)",
            "11": "fraudador(a)",
            "12": "policial"
          },
          "initialLetters": {
            "A": "O último crime do(a)",
            "B": "A traição descoberta",
            "C": "A sombria aventura do(a)",
            "D": "A luta interminável do(a)",
            "E": "O mistério revelado do(a)",
            "F": "O perigoso caso do(a)",
            "G": "A conspiração infinita do(a)",
            "H": "A ameaça inspiradora do(a)",
            "I": "O caos organizado do(a)",
            "J": "A vingança amorosa do(a)",
            "K": "O segredo aberto do(a)",
            "L": "O pecado redimido do(a)",
            "M": "O rastro alarmante do(a)",
            "N": "O legado esquecido do(a)",
            "O": "O divertido clube do(a)",
            "P": "A liga corrupta do(a)",
            "Q": "A desesperança do(a)",
            "R": "O fim do(a)",
            "S": "A ruína do(a)",
            "T": "O crime perfeito do(a)",
            "U": "A dupla máscara do(a)",
            "V": "A sedução abominável do(a)",
            "W": "O desafio desagradável do(a)",
            "X": "A queda horrenda do(a)",
            "Y": "A perdição decente do(a)",
            "Z": "O labirinto sem saída do(a)"
          }
        },
        "political": {
          "daysOfBirth": {
            "1": "corrupto(a)",
            "2": "estratégico(a)",
            "3": "visionário(a)",
            "4": "inovador(a)",
            "5": "que virou um gatinho",
            "6": "perspicaz",
            "7": "que sabia demais",
            "8": "persuasivo(a)",
            "9": "honesto(a)",
            "10": "que afundou o país",
            "11": "que nunca mentiu",
            "12": "corajoso(a)",
            "13": "responsável",
            "14": "diplomático(a)",
            "15": "justo(a)",
            "16": "compassivo(a)",
            "17": "que foi longe demais",
            "18": "articulado(a)",
            "19": "pouco confiável",
            "20": "decidido(a) a fazer um caos",
            "21": "sensato(a)",
            "22": "pragmático(a)",
            "23": "condenado(a)",
            "24": "charmoso(a)",
            "25": "visionário(a)",
            "26": "determinado(a)",
            "27": "que iniciou uma guerra",
            "28": "infiltrado(a)",
            "29": "comprometido(a) com as causas erradas",
            "30": "astuto(a)",
            "31": "carismático(a)"
          },
          "birthMonths": {
            "1": "prefeito(a)",
            "2": "presidente",
            "3": "diplomata",
            "4": "ativista",
            "5": "deputado(a)",
            "6": "governador(a)",
            "7": "rei/rainha",
            "8": "espiã(o)",
            "9": "ditador(a)",
            "10": "ministro(a)",
            "11": "secretário(a)",
            "12": "lobista"
          },
          "initialLetters": {
            "A": "A luta pelo poder do(a)",
            "B": "A voz do povo com um(a)",
            "C": "O destino da nação regida por um(a)",
            "D": "A política defasada de um(a)",
            "E": "A democracia silenciosa do(a)",
            "F": "O desgoverno de um(a)",
            "G": "A corrupção generalizada de um(a)",
            "H": "Os segredos de estado do(a)",
            "I": "A batalha eminente do(a)",
            "J": "A justiça injusta do(a)",
            "K": "O futuro inexistente do(a)",
            "L": "O infeliz renascimento do(a)",
            "M": "A grande crise do(a)",
            "N": "O legado invisível do(a)",
            "O": "A conspiração generalizada do(a)",
            "P": "A calma revolução do(a)",
            "Q": "O impasse moral do(a)",
            "R": "A guerra desarmada do(a)",
            "S": "O regime impensável do(a)",
            "T": "A resistência sofrida do(a)",
            "U": "A liderança improvável de um(a)",
            "V": "O partido oposto do(a)",
            "W": "A ideologia macabra do(a)",
            "X": "O conflito sangrento do(a)",
            "Y": "A falta de coragem do(a)",
            "Z": "A visão limitada do(a)"
          }
        },
        "athletic": {
          "daysOfBirth": {
            "1": "ágil",
            "2": "determinado(a)",
            "3": "resiliente",
            "4": "competitivo(a)",
            "5": "forte",
            "6": "disciplinado(a)",
            "7": "dedicado(a)",
            "8": "que só queria tirar um cochilo",
            "9": "aposentado(a)",
            "10": "atlético(a)",
            "11": "estratégico(a)",
            "12": "treinado pra matar",
            "13": "inimigo(a) do carboidrato",
            "14": "inspirador(a)",
            "15": "fanático(a)",
            "16": "motivado(a) por doce",
            "17": "exemplar",
            "18": "apaixonado(a)",
            "19": "que não sabia perder",
            "20": "viciado(a) em bomba anabolizante",
            "21": "elétrico(a)",
            "22": "corajoso(a)",
            "23": "intensamente louco(a)",
            "24": "astuto(a)",
            "25": "visionário(a)",
            "26": "que virou sedentário(a)",
            "27": "indigno(a)",
            "28": "gloriosamente trágico(a)",
            "29": "poderoso(a) e todo gostoso(a)",
            "30": "imparável",
            "31": "campeã(o)"
          },
          "birthMonths": {
            "1": "atleta",
            "2": "corredor(a)",
            "3": "nadador(a)",
            "4": "lutador(a)",
            "5": "ciclista",
            "6": "treinador(a)",
            "7": "jogador(a)",
            "8": "crossfiteiro(a)",
            "9": "ginasta",
            "10": "skatista",
            "11": "boxeador(a)",
            "12": "surfista"
          },
          "initialLetters": {
            "A": "A divertida jornada do(a)",
            "B": "A feliz derrota do(a)",
            "C": "Os altos e baixos do(a)",
            "D": "A superação do(a)",
            "E": "O desafio forjado do(a)",
            "F": "A gloriosa gafe do(a)",
            "G": "A estranha força do(a)",
            "H": "O misterioso talento do(a)",
            "I": "A conquista sabotada do(a)",
            "J": "Dias de luta e glória de um(a)",
            "K": "A fria paixão do(a)",
            "L": "A queda rasteira do(a)",
            "M": "O espírito indomável do(a)",
            "N": "A vitória improvável do(a)",
            "O": "A habilidade secreta do(a)",
            "P": "A determinação do(a)",
            "Q": "A coragem duvidosa do(a)",
            "R": "O orgulho ferido do(a)",
            "S": "A excelência do(a)",
            "T": "A vitória perdida do(a)",
            "U": "A resistência falida do(a)",
            "V": "A destreza desengonçada do(a)",
            "W": "A maestria do(a)",
            "X": "Os super poderes do(a)",
            "Y": "As lendas reais de um(a)",
            "Z": "A glória olímpica do(a)"
          }
        },
        "artistic": {
          "daysOfBirth": {
            "1": "criativo(a)",
            "2": "sensível",
            "3": "expressivo(a)",
            "4": "imaginativo(a)",
            "5": "apaixonado(a)",
            "6": "inspirador(a)",
            "7": "original",
            "8": "excentrico(a)",
            "9": "sonhador(a)",
            "10": "sensível",
            "11": "harmonioso(a)",
            "12": "visionário(a)",
            "13": "introspectivo(a)",
            "14": "versátil",
            "15": "emotivo(a)",
            "16": "poético(a)",
            "17": "inovador(a)",
            "18": "que usava IA",
            "19": "visionário(a)",
            "20": "imaginativo(a)",
            "21": "criativo(a)",
            "22": "sensível(a)",
            "23": "inspirador(a)",
            "24": "expressivo(a)",
            "25": "apaixonado(a)",
            "26": "sonhador(a)",
            "27": "original",
            "28": "artístico(a)",
            "29": "introspectivo(a)",
            "30": "harmonioso(a)",
            "31": "visionário(a)"
          },
          "birthMonths": {
            "1": "pintor(a)",
            "2": "escultor(a)",
            "3": "idol",
            "4": "ator/atriz",
            "5": "dançarino(a)",
            "6": "escritor(a)",
            "7": "cantor(a)",
            "8": "poeta/poetiza",
            "9": "designer",
            "10": "cineasta",
            "11": "fotógrafo(a)",
            "12": "rapper"
          },
          "initialLetters": {
            "A": "A arte do(a)",
            "B": "A fria expressão do(a)",
            "C": "A falta de criatividade do(a)",
            "D": "O talento adormecido do(a)",
            "E": "A beleza duvidosa do(a)",
            "F": "A terrível inspiração de um(a)",
            "G": "A paixão arrebatadora do(a)",
            "H": "O mundo sombrio do(a)",
            "I": "O olhar 43 do(a)",
            "J": "O suspeito universo do(a)",
            "K": "A mente fechada do(a)",
            "L": "A criação fatal do(a)",
            "M": "A poesia sem rima do(a)",
            "N": "O espírito indomável do(a)",
            "O": "O sonho intrigante do(a)",
            "P": "A grande baixaria do(a)",
            "Q": "A peculiar imaginação do(a)",
            "R": "A eterna busca do(a)",
            "S": "A arte horripilante do(a)",
            "T": "A inspiração do(a)",
            "U": "A obra épica do(a)",
            "V": "A estética hostil do(a)",
            "W": "O mundo interior do(a)",
            "X": "A instável jornada de um(a)",
            "Y": "O imaginário hiperativo de um(a)",
            "Z": "A louca vida de um(a)"
          }
        }

      }
}
